[{"total_issued_vcs":1000,"total_revoked_vcs":100,"false_positive_rate":0.4,"mt_level_in_dlt":3,"mt_depth":11,"number_of_false_positives":387,"number_of_vcs_retrieved_witness_from_issuer":353,"number_of_affected_vcs":11049,"number_of_witness_updates_saved":34,"bloom_filter_size":191,"bloom_filter_indexes_per_entry":2},
  {"total_issued_vcs":1000,"total_revoked_vcs":100,"false_positive_rate":0.4,"mt_level_in_dlt":3,"mt_depth":11,"number_of_false_positives":384,"number_of_vcs_retrieved_witness_from_issuer":353,"number_of_affected_vcs":11176,"number_of_witness_updates_saved":31,"bloom_filter_size":191,"bloom_filter_indexes_per_entry":2},
  {"total_issued_vcs":1000,"total_revoked_vcs":100,"false_positive_rate":0.4,"mt_level_in_dlt":4,"mt_depth":11,"number_of_false_positives":401,"number_of_vcs_retrieved_witness_from_issuer":381,"number_of_affected_vcs":5922,"number_of_witness_updates_saved":20,"bloom_filter_size":191,"bloom_filter_indexes_per_entry":2},
  {"total_issued_vcs":1000,"total_revoked_vcs":100,"false_positive_rate":0.4,"mt_level_in_dlt":4,"mt_depth":11,"number_of_false_positives":437,"number_of_vcs_retrieved_witness_from_issuer":420,"number_of_affected_vcs":5985,"number_of_witness_updates_saved":17,"bloom_filter_size":191,"bloom_filter_indexes_per_entry":2},
  {"total_issued_vcs":1000,"total_revoked_vcs":100,"false_positive_rate":0.4,"mt_level_in_dlt":5,"mt_depth":11,"number_of_false_positives":327,"number_of_vcs_retrieved_witness_from_issuer":323,"number_of_affected_vcs":3100,"number_of_witness_updates_saved":4,"bloom_filter_size":191,"bloom_filter_indexes_per_entry":2},
  {"total_issued_vcs":1000,"total_revoked_vcs":100,"false_positive_rate":0.4,"mt_level_in_dlt":6,"mt_depth":11,"number_of_false_positives":353,"number_of_vcs_retrieved_witness_from_issuer":269,"number_of_affected_vcs":1500,"number_of_witness_updates_saved":84,"bloom_filter_size":191,"bloom_filter_indexes_per_entry":2},
  {"total_issued_vcs":1000,"total_revoked_vcs":100,"false_positive_rate":0.4,"mt_level_in_dlt":7,"mt_depth":11,"number_of_false_positives":399,"number_of_vcs_retrieved_witness_from_issuer":194,"number_of_affected_vcs":700,"number_of_witness_updates_saved":205,"bloom_filter_size":191,"bloom_filter_indexes_per_entry":2},
  {"total_issued_vcs":1000,"total_revoked_vcs":100,"false_positive_rate":0.4,"mt_level_in_dlt":8,"mt_depth":11,"number_of_false_positives":321,"number_of_vcs_retrieved_witness_from_issuer":91,"number_of_affected_vcs":300,"number_of_witness_updates_saved":230,"bloom_filter_size":191,"bloom_filter_indexes_per_entry":2},
  {"total_issued_vcs":1000,"total_revoked_vcs":100,"false_positive_rate":0.4,"mt_level_in_dlt":9,"mt_depth":11,"number_of_false_positives":401,"number_of_vcs_retrieved_witness_from_issuer":42,"number_of_affected_vcs":100,"number_of_witness_updates_saved":359,"bloom_filter_size":191,"bloom_filter_indexes_per_entry":2}]